LICENCE.txt
README.md
setup.py
codigofacilito_vc/__init__.py
codigofacilito_vc/__main__.py
codigofacilito_vc/workshops.py
codigofacilito_vc.egg-info/PKG-INFO
codigofacilito_vc.egg-info/SOURCES.txt
codigofacilito_vc.egg-info/dependency_links.txt
codigofacilito_vc.egg-info/entry_points.txt
codigofacilito_vc.egg-info/requires.txt
codigofacilito_vc.egg-info/top_level.txt
test/tests.py