Metadata-Version: 2.1
Name: codigofacilito_vc
Version: 0.0.2
Summary: Este paquete permite consumir el API de CodigoFacilito
Home-page: https://github.com/VictorContiDesign/codigofacilito_package.git
Author: Victor Joseph Conti Romero
Author-email: victor.conti.dev@gmail.com
License: MIT
Keywords: codigofacilito,miprimerpaquete
Classifier: Development Status :: 3 - Alpha
Classifier: Intended Audience :: Developers
Classifier: Topic :: Software Development :: Build Tools
Classifier: License :: OSI Approved :: MIT License
Classifier: Programming Language :: Python :: 3
License-File: LICENCE.txt
Requires-Dist: requests
